HvH_Maid_API/__init__.py
HvH_Maid_API/authclient.py
HvH_Maid_API/authsrv.crt
HvH_Maid_API/byte_convertor.py
HvH_Maid_API/maid_game_client.py
HvH_Maid_API/messagebuf.py
hvh_maid_api-0.0.10.dist-info/METADATA
hvh_maid_api-0.0.10.dist-info/WHEEL
hvh_maid_api-0.0.10.dist-info/licenses/LICENSE
hvh_maid_api-0.0.10.dist-info/RECORD
