Metadata-Version: 2.4
Name: HvH_Maid_API
Version: 0.0.10
Summary: a python api for haven and hearth game
Author-email: Maid <lisasissy999@gmail.com>
License-File: LICENSE
Classifier: License :: OSI Approved :: MIT License
Classifier: Operating System :: OS Independent
Classifier: Programming Language :: Python :: 3
Requires-Python: >=3.8
